[
  {
    "timestamp": "2025-08-22T01:15:57.628Z",
    "groups": [
      [
        "Sky",
        "Mi"
      ],
      [
        "Tee",
        "Inc"
      ],
      [
        "Chak",
        "Linda"
      ],
      [
        "Aidyn",
        "Ozone"
      ],
      [
        "Punn",
        "Ryu"
      ],
      [
        "Hopper",
        "Vayo"
      ],
      [
        "Gao",
        "Muse"
      ],
      [
        "Don"
      ],
      [
        "Shogun",
        "Proud"
      ],
      [
        "Boon"
      ]
    ],
    "incompatiblePairs": [
      "Shogun|Tee"
    ]
  },
  {
    "timestamp": "2025-08-29T01:22:54.421Z",
    "groups": [
      [
        "Tee",
        "Shogun"
      ],
      [
        "Ryu",
        "Vayo"
      ],
      [
        "Proud",
        "Muse"
      ],
      [
        "Chak",
        "Aidyn"
      ],
      [
        "Gao",
        "Don"
      ],
      [
        "Mi",
        "Linda"
      ],
      [
        "Inc",
        "Sky"
      ],
      [
        "Hopper",
        "Ozone"
      ],
      [
        "Punn",
        "Boon"
      ]
    ],
    "incompatiblePairs": [
      "Shogun|Tee",
      "Punn|Ryu"
    ]
  },
  {
    "timestamp": "2025-08-15T02:01:20.983Z",
    "groups": [
      [
        "Hopper",
        "Ryu"
      ],
      [
        "Muse",
        "Mi"
      ],
      [
        "Shogun",
        "Don"
      ],
      [
        "Ozone",
        "Punn"
      ],
      [
        "Boon",
        "Tee"
      ],
      [
        "Gao",
        "Inc"
      ],
      [
        "Proud",
        "Vayo"
      ],
      [
        "Linda",
        "Aidyn"
      ],
      [
        "Sky",
        "Chak"
      ]
    ],
    "incompatiblePairs": [
      "Shogun|Tee",
      "Punn|Ryu",
      "Ryu|Shogun"
    ]
  },
  {
    "timestamp": "2025-09-10T05:02:41.242Z",
    "groups": [
      [
        "Linda",
        "Don"
      ],
      [
        "Boon",
        "Inc"
      ],
      [
        "Proud",
        "Mi"
      ],
      [
        "Punn",
        "Hopper"
      ],
      [
        "Tee",
        "Sky"
      ],
      [
        "Muse",
        "Chak"
      ],
      [
        "Gao",
        "Shogun"
      ],
      [
        "Ryu",
        "Ozone"
      ],
      [
        "Aidyn",
        "Vayo"
      ]
    ],
    "incompatiblePairs": [
      "Shogun|Tee",
      "Punn|Ryu",
      "Ryu|Shogun",
      "Boon|Ozone",
      "Chak|Gao"
    ]
  },
  {
    "timestamp": "2025-09-24T05:23:04.498Z",
    "groups": [
      [
        "Aidyn",
        "Boon"
      ],
      [
        "Mi",
        "Don"
      ],
      [
        "Linda",
        "Ryu"
      ],
      [
        "Vayo",
        "Shogun"
      ],
      [
        "Inc",
        "Hopper"
      ],
      [
        "Proud",
        "Gao"
      ],
      [
        "Chak",
        "Tee"
      ],
      [
        "Ozone",
        "Punn"
      ],
      [
        "Sky",
        "Muse"
      ]
    ],
    "incompatiblePairs": [
      "Shogun|Tee",
      "Punn|Ryu",
      "Ryu|Shogun",
      "Boon|Ozone",
      "Chak|Gao"
    ]
  },
  {
    "timestamp": "2025-10-16T06:57:14.560Z",
    "groups": [
      [],
      [
        "Punn",
        "Proud"
      ],
      [
        "Inc",
        "Ozone"
      ],
      [
        "Muse",
        "Sky"
      ],
      [
        "Mi",
        "Tee"
      ],
      [
        "Vayo",
        "Boon"
      ],
      [
        "Shogun",
        "Hopper"
      ],
      [],
      [
        "Ryu",
        "Gao"
      ],
      [
        "Don",
        "Chak"
      ],
      [],
      [
        "Aidyn",
        "Linda"
      ]
    ],
    "incompatiblePairs": [
      "Shogun|Tee",
      "Punn|Ryu",
      "Ryu|Shogun",
      "Boon|Ozone",
      "Chak|Gao"
    ]
  },
  {
    "timestamp": "2025-10-16T07:00:51.677Z",
    "groups": [
      [],
      [
        "Punn",
        "Proud"
      ],
      [
        "Inc",
        "Ozone"
      ],
      [
        "Tee",
        "Mi"
      ],
      [
        "Muse",
        "Sky"
      ],
      [
        "Vayo",
        "Boon"
      ],
      [
        "Hopper",
        "Shogun"
      ],
      [],
      [
        "Ryu",
        "Gao"
      ],
      [
        "Linda",
        "Aidyn"
      ],
      [],
      [
        "Don",
        "Chak"
      ]
    ],
    "incompatiblePairs": [
      "Shogun|Tee",
      "Punn|Ryu",
      "Ryu|Shogun",
      "Boon|Ozone",
      "Chak|Gao"
    ]
  },
  {
    "timestamp": "2025-10-22T02:39:00.563Z",
    "groups": [
      [],
      [
        "Punn",
        "Proud"
      ],
      [
        "Inc",
        "Ozone"
      ],
      [
        "Tee",
        "Mi"
      ],
      [
        "Muse",
        "Sky"
      ],
      [
        "Vayo",
        "Boon"
      ],
      [
        "Hopper",
        "Shogun"
      ],
      [],
      [
        "Ryu",
        "Gao"
      ],
      [
        "Linda",
        "Aidyn"
      ],
      [],
      [
        "Don",
        "Chak"
      ]
    ],
    "incompatiblePairs": [
      "Shogun|Tee",
      "Punn|Ryu",
      "Ryu|Shogun",
      "Boon|Ozone",
      "Chak|Gao"
    ]
  }
]